kuyruk_manager/__init__.py
kuyruk_manager/templates/failed_tasks.html
kuyruk_manager/templates/layout.html
kuyruk_manager/templates/workers.html
Kuyruk_Manager-4.0.0.dist-info/LICENSE
Kuyruk_Manager-4.0.0.dist-info/METADATA
Kuyruk_Manager-4.0.0.dist-info/WHEEL
Kuyruk_Manager-4.0.0.dist-info/entry_points.txt
Kuyruk_Manager-4.0.0.dist-info/top_level.txt
Kuyruk_Manager-4.0.0.dist-info/RECORD
