Metadata-Version: 2.1
Name: Kuyruk-Manager
Version: 4.0.0
Summary: Manage Kuyruk workers.
Home-page: https://github.com/cenkalti/kuyruk-manager
Author: Cenk Altı
Author-email: cenkalti@gmail.com
Keywords: kuyruk manager
Classifier: Development Status :: 5 - Production/Stable
Classifier: License :: OSI Approved :: MIT License
Classifier: Operating System :: OS Independent
Classifier: Programming Language :: Python
Classifier: Programming Language :: Python :: 3
Classifier: Topic :: Software Development :: Object Brokering
Classifier: Topic :: System :: Distributed Computing
License-File: LICENSE
Requires-Dist: kuyruk >=10.0.1
Requires-Dist: redis >=2.10
Requires-Dist: Flask >=0.10
Requires-Dist: waitress >=1.0.2
